README.md
setup.py
in10t_api_client/__init__.py
in10t_api_client/api_client.py
in10t_api_client/configuration.py
in10t_api_client/rest.py
in10t_api_client.egg-info/PKG-INFO
in10t_api_client.egg-info/SOURCES.txt
in10t_api_client.egg-info/dependency_links.txt
in10t_api_client.egg-info/requires.txt
in10t_api_client.egg-info/top_level.txt
in10t_api_client/api/__init__.py
in10t_api_client/api/data_api.py
in10t_api_client/api/file_data_api.py
in10t_api_client/api/files_api.py
in10t_api_client/api/security_api.py
in10t_api_client/api/shapefile_data_api.py
in10t_api_client/api/trial_ids_api.py
in10t_api_client/api/trials_api.py
in10t_api_client/models/__init__.py
in10t_api_client/models/access_token.py
in10t_api_client/models/as_applied_data.py
in10t_api_client/models/as_applied_data_item.py
in10t_api_client/models/harvest_data.py
in10t_api_client/models/harvest_data_item.py
in10t_api_client/models/planting_data.py
in10t_api_client/models/planting_data_item.py
in10t_api_client/models/processed_harvest_data.py
in10t_api_client/models/processed_harvest_data_item.py
in10t_api_client/models/token_credentials.py
in10t_api_client/models/trial_id_lookup_item.py
test/__init__.py
test/test_access_token.py
test/test_as_applied_data.py
test/test_as_applied_data_item.py
test/test_data_api.py
test/test_harvest_data.py
test/test_harvest_data_item.py
test/test_planting_data.py
test/test_planting_data_item.py
test/test_processed_harvest_data.py
test/test_processed_harvest_data_item.py
test/test_security_api.py
test/test_shapefile_data_api.py
test/test_token_credentials.py
test/test_trial_id_lookup_item.py
test/test_trial_ids_api.py