Metadata-Version: 1.0
Name: in10t-api-client
Version: 1.0.4
Summary: IN10T Client Data API
Home-page: UNKNOWN
Author: UNKNOWN
Author-email: matt@in10t.ag
License: UNKNOWN
Keywords: Swagger,IN10T Client Data API
Platform: UNKNOWN
